dkcore/__init__.py
dkcore/core.py
dkcore/listen.py
DkCorePy-0.1.5.dist-info/LICENSE
DkCorePy-0.1.5.dist-info/METADATA
DkCorePy-0.1.5.dist-info/NOTICE
DkCorePy-0.1.5.dist-info/WHEEL
DkCorePy-0.1.5.dist-info/top_level.txt
DkCorePy-0.1.5.dist-info/RECORD
