Metadata-Version: 2.1
Name: DkCorePy
Version: 0.1.5
Summary: DkCore Library - DkCore Self Library for Python.
Home-page: https://github.com/npdkdev/dkcorepy
Author: DkDev
Author-email: 
License: GPL-3.0
Project-URL: Bug Tracker, https://github.com/npdkdev/dkcorepy/issues
Project-URL: Source Code, https://github.com/npdkdev/dkcorepy
Classifier: Programming Language :: Python :: 3
Classifier: Programming Language :: Python :: 3.8
Classifier: Programming Language :: Python :: 3.9
Classifier: Programming Language :: Python :: 3.10
Classifier: Programming Language :: Python :: 3.11
Classifier: License :: OSI Approved :: GNU General Public License v3 (GPLv3)
Classifier: Operating System :: OS Independent
Requires-Python: ~=3.7
License-File: LICENSE
License-File: NOTICE
